google/fhir/r4/__init__.py
google/fhir/r4/fhir_path.py
google/fhir/r4/fhir_path_test.py
google/fhir/r4/json_format.py
google/fhir/r4/primitive_handler.py
google/fhir/r4/r4_package.py
google/fhir/r4/r4_package_test.py
google/fhir/r4/references_test.py
google/fhir/r4/resource_validation.py
google/fhir/r4/data/hl7.fhir.r4.core.tgz
google/fhir/r4/fhir_client/__init__.py
google/fhir/r4/fhir_client/_fhir_client.py
google/fhir/r4/fhir_client/_fhir_client_test.py
google/fhir/r4/fhir_client/fhir_client.py
google/fhir/r4/fhir_client/fhir_client_test.py
google/fhir/r4/proto/__init__.py
google/fhir/r4/proto/fhirproto_extensions_pb2.py
google/fhir/r4/proto/fhirproto_pb2.py
google/fhir/r4/proto/google_extensions_pb2.py
google/fhir/r4/proto/ml_extensions_pb2.py
google/fhir/r4/proto/primitive_test_suite_pb2.py
google/fhir/r4/proto/uscore_codes_pb2.py
google/fhir/r4/proto/uscore_pb2.py
google/fhir/r4/proto/core/__init__.py
google/fhir/r4/proto/core/codes_pb2.py
google/fhir/r4/proto/core/datatypes_pb2.py
google/fhir/r4/proto/core/extensions_pb2.py
google/fhir/r4/proto/core/valuesets_pb2.py
google/fhir/r4/proto/core/resources/__init__.py
google/fhir/r4/proto/core/resources/account_pb2.py
google/fhir/r4/proto/core/resources/activity_definition_pb2.py
google/fhir/r4/proto/core/resources/adverse_event_pb2.py
google/fhir/r4/proto/core/resources/allergy_intolerance_pb2.py
google/fhir/r4/proto/core/resources/appointment_pb2.py
google/fhir/r4/proto/core/resources/appointment_response_pb2.py
google/fhir/r4/proto/core/resources/audit_event_pb2.py
google/fhir/r4/proto/core/resources/basic_pb2.py
google/fhir/r4/proto/core/resources/binary_pb2.py
google/fhir/r4/proto/core/resources/biologically_derived_product_pb2.py
google/fhir/r4/proto/core/resources/body_structure_pb2.py
google/fhir/r4/proto/core/resources/bundle_and_contained_resource_pb2.py
google/fhir/r4/proto/core/resources/capability_statement_pb2.py
google/fhir/r4/proto/core/resources/care_plan_pb2.py
google_fhir_r4-0.11.0.dist-info/METADATA
google_fhir_r4-0.11.0.dist-info/WHEEL
google_fhir_r4-0.11.0.dist-info/top_level.txt
google_fhir_r4-0.11.0.dist-info/RECORD
